{
  "test/unit/AllTests-dbg.js": 1617110074000,
  "test/integration/NavigationJourney.js": 1617110074000,
  "test/unit/controller/App.controller.js": 1617110074000,
  "test/integration/pages/App.js": 1617110074000,
  "test/integration/arrangements/Startup.js": 1617110074000,
  "test/unit/unitTests.qunit.js": 1617110074000,
  "test/unit/AllTests.js": 1617110074000,
  "test/integration/opaTests.qunit.js": 1617110074000,
  "manifest.json": 1617123710485,
  "test/integration/AllJourneys.js": 1617110074000,
  "test/testsuite.qunit.js": 1617110074000,
  "model/models.js": 1617110074000,
  "controller/App.controller.js": 1617122653282,
  "Component.js": 1617110074000,
  "manifest-bundle.zip": 1617123710521,
  "Component-preload.js": 1617123710848,
  "test/testsuite.qunit-dbg.js": 1617110074000,
  "test/integration/pages/App-dbg.js": 1617110074000,
  "test/integration/arrangements/Startup-dbg.js": 1617110074000,
  "test/unit/unitTests.qunit-dbg.js": 1617110074000,
  "i18n/i18n.properties": 1617110074000,
  "test/integration/opaTests.qunit-dbg.js": 1617110074000,
  "test/integration/NavigationJourney-dbg.js": 1617110074000,
  "test/integration/AllJourneys-dbg.js": 1617110074000,
  "test/unit/controller/App-dbg.controller.js": 1617110074000,
  "model/models-dbg.js": 1617110074000,
  "controller/App-dbg.controller.js": 1617122653282,
  "Component-dbg.js": 1617110074000,
  "neo-app.json": 1617123711236,
  "di.code-validation.core_issues.json": 1617123722272,
  "resources.json": 1617123722294,
  "test/unit/unitTests.qunit.html": 1617110074000,
  "test/integration/opaTests.qunit.html": 1617110074000,
  "view/App.view.xml": 1617122622692,
  "test/testsuite.qunit.html": 1617110074000,
  "css/style.css": 1617110074000,
  "index.html": 1617121421559
}